tor_search/__init__.py
tor_search/cli.py
tor_search/searcher.py
tor_search-0.1.2.dist-info/licenses/LICENSE
tor_search-0.1.2.dist-info/METADATA
tor_search-0.1.2.dist-info/WHEEL
tor_search-0.1.2.dist-info/entry_points.txt
tor_search-0.1.2.dist-info/top_level.txt
tor_search-0.1.2.dist-info/RECORD
